LICENSE
MANIFEST.in
README.md
pyproject.toml
setup.py
OptiStradex.egg-info/PKG-INFO
OptiStradex.egg-info/SOURCES.txt
OptiStradex.egg-info/dependency_links.txt
OptiStradex.egg-info/top_level.txt
optistradex/__init__.py
optistradex/__main__.py
optistradex/universe.py
optistradex/config/__init__.py
optistradex/config/enumeration.py
optistradex/config/parser.py
optistradex/engine/__init__.py
optistradex/exchange/__init__.py
optistradex/exchange/exchange.py
optistradex/exchange/base/__init__.py
optistradex/exchange/base/market_data.py
optistradex/exchange/base/order_entry.py
optistradex/exchange/ib/__init__.py
optistradex/exchange/ib/ib.py
optistradex/strategy/__init__.py
optistradex/strategy/plot.py
optistradex/strategy/portfolio.py
optistradex/strategy/risk.py
optistradex/strategy/strategy.py
optistradex/strategy/util.py