Metadata-Version: 2.1
Name: OptiStradex
Version: 0.0.1
Summary: Asynchronous Event-driven Algorithmic Trading Library
Home-page: https://github.com/jialuechen/optiStradex
Author: Jialue Chen
Author-email: jialuechen@outlook.com
License-File: LICENSE
